chatterbox_bus_client/__init__.py
chatterbox_bus_client/__main__.py
chatterbox_bus_client/client.py
chatterbox_bus_client/conf.py
chatterbox_bus_client/encryption.py
chatterbox_bus_client/message.py
chatterbox_bus_client/scheduler.py
chatterbox_bus_client/send_func.py
chatterbox_bus_client/util.py
chatterbox_bus_client-0.0.11.dist-info/LICENSE.md
chatterbox_bus_client-0.0.11.dist-info/METADATA
chatterbox_bus_client-0.0.11.dist-info/WHEEL
chatterbox_bus_client-0.0.11.dist-info/top_level.txt
chatterbox_bus_client-0.0.11.dist-info/RECORD
