Metadata-Version: 2.1
Name: chatterbox-bus-client
Version: 0.0.11
Summary: Chatterbox Messagebus Client
Home-page: https://github.com/HelloChatterbox/chatterbox-bus-client
Author: Kevin Elgan
Author-email: kevin@hellochatterbox.com
License: Apache-2.0
Platform: UNKNOWN
Classifier: Development Status :: 4 - Beta
Classifier: Intended Audience :: Developers
Classifier: License :: OSI Approved :: Apache Software License
Classifier: Programming Language :: Python :: 3.6
Classifier: Programming Language :: Python :: 3.7
Classifier: Programming Language :: Python :: 3.8
Classifier: Programming Language :: Python :: 3.9
License-File: LICENSE.md
Requires-Dist: mycroft-messagebus-client>=0.9.1
Requires-Dist: pyxdg
Requires-Dist: combo-lock>=0.1.1
